swescribe/__about__.py
swescribe/__init__.py
swescribe/__main__.py
swescribe/alignment_to_srt.py
swescribe/clean_whisper.py
swescribe/mpg_to_wav.py
swescribe/paths.py
swescribe/srt_to_txt.py
swescribe/transcribe.py
swescribe/wavpath_to_srt.py
swescribe/wer.py
swescribe-0.1.0.dist-info/METADATA
swescribe-0.1.0.dist-info/WHEEL
swescribe-0.1.0.dist-info/entry_points.txt
swescribe-0.1.0.dist-info/licenses/LICENSE
swescribe-0.1.0.dist-info/RECORD
