Metadata-Version: 2.4
Name: swescribe
Version: 0.1.0
Summary: A WhisperX-powered tool for automatically transcribing speech in historical Swedish newsreels
Project-URL: Homepage, https://github.com/Modern36/swescribe
Project-URL: Repository, https://github.com/Modern36/swescribe
Project-URL: Bug Tracker, https://github.com/Modern36/swescribe/issues
Author-email: Robert Aspenskog <robert.aspenskog@gmail.com>, Mathias Johansson <MathiasJoha@gmail.com>
Maintainer-email: Mathias Johansson <MathiasJoha@gmail.com>, Robert Aspenskog <robert.aspenskog@gmail.com>
License: Attribution-NonCommercial 4.0 International
License-File: LICENSE
Keywords: automatic speech recognition,newsreels,speech-to-text,swedish,transcription,whisperx
Classifier: Development Status :: 4 - Beta
Classifier: Environment :: GPU :: NVIDIA CUDA
Classifier: Framework :: Pytest
Classifier: Intended Audience :: Science/Research
Classifier: Programming Language :: Python :: 3.10
Classifier: Topic :: Multimedia :: Sound/Audio :: Analysis
Classifier: Topic :: Multimedia :: Sound/Audio :: Speech
Classifier: Topic :: Multimedia :: Video
Classifier: Topic :: Scientific/Engineering :: Artificial Intelligence
Classifier: Topic :: Utilities
Requires-Python: <3.11,>=3.10
Requires-Dist: jiwer==3.1.0
Requires-Dist: numpy<2,>=1.22
Requires-Dist: pandas==2.2.3
Requires-Dist: tqdm==4.67.1
Provides-Extra: dev
Requires-Dist: coverage-badge==1.1.2; extra == 'dev'
Requires-Dist: coverage==7.5.1; extra == 'dev'
Requires-Dist: hatch==1.14.1; extra == 'dev'
Requires-Dist: pytest-cov==5.0.0; extra == 'dev'
Requires-Dist: pytest-xdist==3.6.1; extra == 'dev'
Requires-Dist: pytest==8.2.0; extra == 'dev'
Requires-Dist: tox==4.25.0; extra == 'dev'
Provides-Extra: whisperx
Requires-Dist: ctranslate2==4.4.0; extra == 'whisperx'
Requires-Dist: pyannote-audio; extra == 'whisperx'
Requires-Dist: torch; extra == 'whisperx'
Requires-Dist: torchaudio; extra == 'whisperx'
Requires-Dist: whisperx; extra == 'whisperx'
